{
	"class" : {
		"kAbbreviations" : "jupiter 4/22/2011 09:05",
		"kBLIPCompressed" : "jupiter 4/22/2011 09:21",
		"kBLIPError" : "jupiter 4/22/2011 09:21",
		"kBLIPErrorBadFrame" : "jupiter 4/22/2011 09:23",
		"kBLIPErrorBadRange" : "jupiter 4/22/2011 09:24",
		"kBLIPErrorBadRequest" : "jupiter 4/22/2011 09:24",
		"kBLIPErrorDisconnected" : "jupiter 4/22/2011 09:24",
		"kBLIPErrorForbidden" : "jupiter 4/22/2011 09:24",
		"kBLIPErrorHandlerFailed" : "jupiter 4/22/2011 09:24",
		"kBLIPErrorMisc" : "jupiter 4/22/2011 09:24",
		"kBLIPErrorNotFound" : "jupiter 4/22/2011 09:25",
		"kBLIPErrorPeerNotAllowed" : "jupiter 4/22/2011 09:25",
		"kBLIPErrorUnspecified" : "jupiter 4/22/2011 09:25",
		"kBLIPFrameHeaderProtocolVersion" : "jupiter 4/22/2011 09:26",
		"kBLIPMessage" : "jupiter 4/22/2011 09:22",
		"kBLIPMeta" : "jupiter 4/22/2011 09:25",
		"kBLIPMoreComing" : "jupiter 4/22/2011 09:26",
		"kBLIPNoReply" : "jupiter 4/22/2011 09:26",
		"kBLIPProfileCloseConnection" : "jupiter 4/22/2011 09:27",
		"kBLIPProfileOpenConnection" : "jupiter 4/22/2011 09:27",
		"kBLIPReply" : "jupiter 4/22/2011 09:22",
		"kBLIPTypeMask" : "jupiter 4/22/2011 09:26",
		"kBLIPUrgent" : "jupiter 4/22/2011 09:26",
		"kDefaultFrameSize" : "jupiter 4/22/2011 09:04",
		"kMessageTypes" : "jupiter 4/22/2011 09:05" },
	"instance" : {
		"dispatchMetaRequest:" : "jupiter 4/22/2011 09:28",
		"dispatchRequest:" : "jupiter 4/22/2011 09:29",
		"dispatchResponse:" : "jupiter 4/22/2011 09:29",
		"dispatcher" : "jupiter 4/23/2011 05:35",
		"dispatcherClass" : "jupiter 4/23/2011 05:35",
		"handleCloseRequest:" : "jupiter 4/23/2011 05:37",
		"readerClass" : "jupiter 4/23/2011 05:33",
		"writerClass" : "jupiter 4/23/2011 05:33" } }
